odoo/addons/delivery_procurement_group_carrier/README.rst
odoo/addons/delivery_procurement_group_carrier/__init__.py
odoo/addons/delivery_procurement_group_carrier/__manifest__.py
odoo/addons/delivery_procurement_group_carrier/i18n/delivery_procurement_group_carrier.pot
odoo/addons/delivery_procurement_group_carrier/i18n/es.po
odoo/addons/delivery_procurement_group_carrier/i18n/it.po
odoo/addons/delivery_procurement_group_carrier/i18n/pt_BR.po
odoo/addons/delivery_procurement_group_carrier/models/__init__.py
odoo/addons/delivery_procurement_group_carrier/models/procurement_group.py
odoo/addons/delivery_procurement_group_carrier/models/sale_order.py
odoo/addons/delivery_procurement_group_carrier/models/sale_order_line.py
odoo/addons/delivery_procurement_group_carrier/models/stock_move.py
odoo/addons/delivery_procurement_group_carrier/models/stock_picking.py
odoo/addons/delivery_procurement_group_carrier/readme/CONTRIBUTORS.md
odoo/addons/delivery_procurement_group_carrier/readme/CREDITS.md
odoo/addons/delivery_procurement_group_carrier/readme/DESCRIPTION.md
odoo/addons/delivery_procurement_group_carrier/static/description/icon.png
odoo/addons/delivery_procurement_group_carrier/static/description/index.html
odoo/addons/delivery_procurement_group_carrier/static/src/scss/report_delivery_slip.scss
odoo/addons/delivery_procurement_group_carrier/tests/__init__.py
odoo/addons/delivery_procurement_group_carrier/tests/common.py
odoo/addons/delivery_procurement_group_carrier/tests/test_carrier.py
odoo/addons/delivery_procurement_group_carrier/tests/test_return.py
odoo/addons/delivery_procurement_group_carrier/views/procurement_group.xml
odoo/addons/delivery_procurement_group_carrier/wizards/__init__.py
odoo/addons/delivery_procurement_group_carrier/wizards/stock_return_picking.py
odoo_addon_delivery_procurement_group_carrier-18.0.1.0.3.dist-info/METADATA
odoo_addon_delivery_procurement_group_carrier-18.0.1.0.3.dist-info/WHEEL
odoo_addon_delivery_procurement_group_carrier-18.0.1.0.3.dist-info/top_level.txt
odoo_addon_delivery_procurement_group_carrier-18.0.1.0.3.dist-info/RECORD
